{"nodes": [{"name": "Butter0", "label": "Butter", "category": "first", "colour": "#d1e1c6", "layer": 0, "emission": 5.535941335900963}, {"label": "Electricity", "name": "Electricity", "category": "SBTs subcategories", "colour": "#829488", "layer": 3, "emission": 0.5756142826473978}, {"label": "Scope 1", "name": "Scope 1", "category": "SBTs categories", "colour": "#90abd0", "layer": 4, "emission": 0.2588236329958269}, {"label": "Heat and steam", "name": "Heat and steam", "category": "SBTs subcategories", "colour": "#829488", "layer": 3, "emission": 0.1513149775472824}, {"label": "Capital assets", "name": "Capital assets", "category": "SBTs subcategories", "colour": "#829488", "layer": 3, "emission": 0.038126620180662485}, {"label": "Scope 3", "name": "Scope 3", "category": "SBTs categories", "colour": "#90abd0", "layer": 4, "emission": 4.808982091632031}, {"label": "Purchased other goods and services", "name": "Purchased other goods and services", "category": "SBTs subcategories", "colour": "#829488", "layer": 3, "emission": 0.15978116667122944}, {"label": "Waste", "name": "Waste", "category": "SBTs subcategories", "colour": "#829488", "layer": 3, "emission": 0.014667087410185964}, {"name": "Cream1", "label": "Cream", "category": "Butter", "colour": "#d4d7e6", "layer": 1, "emission": 5.230779308904372}, {"label": "Production Processes", "name": "Production Processes", "category": "SBTs categories", "colour": "#829488", "layer": 3, "emission": 2.998407420395921e-05}, {"label": "Scope 2", "name": "Scope 2", "category": "SBTs categories", "colour": "#90abd0", "layer": 4, "emission": 0.46813561127305725}, {"label": "Agri-food goods", "name": "Agri-food goods", "category": "SBTs subcategories", "colour": "#829488", "layer": 3, "emission": 4.582053874537775}, {"label": "Agricultural services", "name": "Agricultural services", "category": "SBTs subcategories", "colour": "#829488", "layer": 3, "emission": 0.01417935916765245}, {"label": "Transport and distribution", "name": "Transport and distribution", "category": "SBTs subcategories", "colour": "#829488", "layer": 3, "emission": 0.00017398366452603398}, {"name": "Cow milk2", "label": "Cow milk", "category": "Cream", "colour": "#d1a58d", "layer": 2, "emission": 4.311775378077785}, {"name": "Crops2", "label": "Crops", "category": "Cream", "colour": "#d1a58d", "layer": 2, "emission": 0.06917819414514081}, {"label": "Transparent", "name": "Transparent", "category": "Transparency", "colour": "#8a8e91", "layer": 5, "emission": 0.7269592442688841}, {"label": "End of System", "name": "Semi-Transparent", "category": "Transparency", "colour": "#8a8e91", "layer": 5, "emission": 0.42802851940910536}, {"label": "Non-Transparent", "name": "Non-Transparent", "category": "Transparency", "colour": "#8a8e91", "layer": 5, "emission": 4.380953572222926}], "edges": [{"source": "Butter0", "target": "Electricity", "value": 0.19612957122646968}, {"source": "Electricity", "target": "Scope 1", "value": 0.19612957122646968}, {"source": "Butter0", "target": "Heat and steam", "value": 0.06266407769515325}, {"source": "Heat and steam", "target": "Scope 1", "value": 0.06266407769515325}, {"source": "Butter0", "target": "Capital assets", "value": 0.038126620180662485}, {"source": "Capital assets", "target": "Scope 3", "value": 0.038126620180662485}, {"source": "Butter0", "target": "Purchased other goods and services", "value": 0.006398331190948348}, {"source": "Purchased other goods and services", "target": "Scope 3", "value": 0.15978116667122944}, {"source": "Butter0", "target": "Waste", "value": 0.00184342670330917}, {"source": "Waste", "target": "Scope 3", "value": 0.014667087410185964}, {"source": "Butter0", "target": "Cream1", "value": 5.23077930890442}, {"source": "Cream1", "target": "Production Processes", "value": 2.998407420395921e-05}, {"source": "Cream1", "target": "Electricity", "value": 0.3794847114209281}, {"source": "Electricity", "target": "Scope 2", "value": 0.3794847114209281}, {"source": "Cream1", "target": "Purchased other goods and services", "value": 0.1533828354802811}, {"source": "Cream1", "target": "Agri-food goods", "value": 0.201100302314849}, {"source": "Agri-food goods", "target": "Scope 3", "value": 4.582053874537775}, {"source": "Cream1", "target": "Heat and steam", "value": 0.08865089985212915}, {"source": "Heat and steam", "target": "Scope 2", "value": 0.08865089985212915}, {"source": "Cream1", "target": "Agricultural services", "value": 0.01417935916765245}, {"source": "Agricultural services", "target": "Scope 3", "value": 0.01417935916765245}, {"source": "Cream1", "target": "Waste", "value": 0.012823660706876794}, {"source": "Cream1", "target": "Transport and distribution", "value": 0.00017398366452603398}, {"source": "Transport and distribution", "target": "Scope 3", "value": 0.00017398366452603398}, {"source": "Cream1", "target": "Cow milk2", "value": 4.311775378077785}, {"source": "Cow milk2", "target": "Agri-food goods", "value": 4.311775378077785}, {"source": "Cream1", "target": "Crops2", "value": 0.06917819414514081}, {"source": "Crops2", "target": "Agri-food goods", "value": 0.06917819414514081}, {"source": "Scope 1", "target": "Transparent", "value": 0.2588236329958269}, {"source": "Scope 2", "target": "Transparent", "value": 0.46813561127305725}, {"source": "Scope 3", "target": "Semi-Transparent", "value": 0.42802851940910536}, {"source": "Scope 3", "target": "Non-Transparent", "value": 4.380953572222926}, {"source": "Production Processes", "target": "Scope 1", "value": 2.998407420395921e-05}], "emission": 5.535941335900963}